idevenv/__init__.py
idevenv/_utils.py
idevenv/syspath.py
idevenv-0.1.1.dist-info/LICENSE
idevenv-0.1.1.dist-info/METADATA
idevenv-0.1.1.dist-info/WHEEL
idevenv-0.1.1.dist-info/top_level.txt
idevenv-0.1.1.dist-info/RECORD
