Metadata-Version: 2.1
Name: idevenv
Version: 0.1.1
Summary: iDevEnv (Innovata Development Environment)
Home-page: https://github.com/innovata/idevenv
Author: innovata sambong
Author-email: iinnovata@gmail.com
Classifier: Programming Language :: Python :: 3
Classifier: License :: OSI Approved :: MIT License
Classifier: Operating System :: OS Independent
Requires-Python: >=3.8
License-File: LICENSE
